{
  "coord": {
    "lon": 100.5167,
    "lat": 13.75
  },
  "weather": [
    {
      "id": 804,
      "main": "Clouds",
      "description": "overcast clouds",
      "icon": "04d"
    }
  ],
  "base": "stations",
  "main": {
    "temp": 36.35,
    "feels_like": 43.35,
    "temp_min": 32.94,
    "temp_max": 36.64,
    "pressure": 1004,
    "humidity": 53,
    "sea_level": 1004,
    "grnd_level": 1003
  },
  "visibility": 10000,
  "wind": {
    "speed": 5.23,
    "deg": 184,
    "gust": 5.12
  },
  "clouds": {
    "all": 97
  },
  "dt": 1778839748,
  "sys": {
    "type": 2,
    "id": 2073525,
    "country": "TH",
    "sunrise": 1778799098,
    "sunset": 1778845025
  },
  "timezone": 25200,
  "id": 1609350,
  "name": "Bangkok",
  "cod": 200,
  "_last_updated_utc": "2026-05-15T10:14:18.669Z"
}