{
  "coord": {
    "lon": 100.5167,
    "lat": 13.75
  },
  "weather": [
    {
      "id": 804,
      "main": "Clouds",
      "description": "overcast clouds",
      "icon": "04n"
    }
  ],
  "base": "stations",
  "main": {
    "temp": 27.73,
    "feels_like": 31.57,
    "temp_min": 27.73,
    "temp_max": 27.73,
    "pressure": 1006,
    "humidity": 81,
    "sea_level": 1006,
    "grnd_level": 1006
  },
  "visibility": 10000,
  "wind": {
    "speed": 4.04,
    "deg": 266,
    "gust": 8.55
  },
  "clouds": {
    "all": 100
  },
  "dt": 1782673519,
  "sys": {
    "type": 2,
    "id": 2105433,
    "country": "TH",
    "sunrise": 1782687198,
    "sunset": 1782733744
  },
  "timezone": 25200,
  "id": 1609350,
  "name": "Bangkok",
  "cod": 200,
  "_last_updated_utc": "2026-06-28T19:05:19.452Z"
}